CHANGES.rst
LICENSE
MANIFEST.in
README.rst
setup.py
Flask_Test.egg-info/PKG-INFO
Flask_Test.egg-info/SOURCES.txt
Flask_Test.egg-info/dependency_links.txt
Flask_Test.egg-info/not-zip-safe
Flask_Test.egg-info/requires.txt
Flask_Test.egg-info/top_level.txt
docs/Makefile
docs/conf.py
docs/index.rst
docs/make.bat
flask_test/__init__.py
flask_test/base.py
flask_test/database.py
flask_test/view.py
tests/__init__.py
tests/test_class_level_setup.py
tests/test_database_setup.py
tests/test_integration_setup.py
tests/test_view_setup.py